ckantools/__init__.py
ckantools/config.py
ckantools/loaders.py
ckantools/timer.py
ckantools/vars.py
ckantools/decorators/__init__.py
ckantools/decorators/actions.py
ckantools/decorators/auth.py
ckantools/decorators/validators.py
ckantools/utils/__init__.py
ckantools/utils/strings.py
ckantools/validators/__init__.py
ckantools/validators/ivalidators.py
ckantools/validators/misc.py
ckantools-0.4.2.dist-info/licenses/LICENSE
docs/_scripts/gen_api_pages.py
ckantools-0.4.2.dist-info/METADATA
ckantools-0.4.2.dist-info/WHEEL
ckantools-0.4.2.dist-info/top_level.txt
ckantools-0.4.2.dist-info/RECORD
